README.md
setup.py
chirpstack_api/__init__.py
chirpstack_api/api/__init__.py
chirpstack_api/api/application_pb2.py
chirpstack_api/api/application_pb2_grpc.py
chirpstack_api/api/device_pb2.py
chirpstack_api/api/device_pb2_grpc.py
chirpstack_api/api/device_profile_pb2.py
chirpstack_api/api/device_profile_template_pb2.py
chirpstack_api/api/device_profile_template_pb2_grpc.py
chirpstack_api/api/frame_log_pb2.py
chirpstack_api/api/gateway_pb2.py
chirpstack_api/api/gateway_pb2_grpc.py
chirpstack_api/api/internal_pb2.py
chirpstack_api/api/multicast_group_pb2.py
chirpstack_api/api/tenant_pb2.py
chirpstack_api/api/user_pb2.py
chirpstack_api/common/__init__.py
chirpstack_api/common/common_pb2.py
chirpstack_api/gw/__init__.py
chirpstack_api/gw/gw_pb2.py
chirpstack_api/integration/__init__.py
chirpstack_api/integration/integration_pb2.py
chirpstack_api/meta/__init__.py
chirpstack_api/meta/meta_pb2.py
chirpstack_api_beta.egg-info/PKG-INFO
chirpstack_api_beta.egg-info/SOURCES.txt
chirpstack_api_beta.egg-info/dependency_links.txt
chirpstack_api_beta.egg-info/not-zip-safe
chirpstack_api_beta.egg-info/requires.txt
chirpstack_api_beta.egg-info/top_level.txt