Metadata-Version: 2.1
Name: chirpstack-api-beta
Version: 4.16
Summary: Chirpstack Python API
Home-page: https://github.com/chirpstack/chirpstack/tree/master/api/
Author: Orne Brocaar
Author-email: info@brocaar.com
License: MIT
Platform: UNKNOWN
Classifier: Intended Audience :: Developers
Classifier: Operating System :: OS Independent
Classifier: Programming Language :: Python :: 3.7
Classifier: Topic :: Communications
Classifier: Topic :: Software Development
Classifier: Topic :: Software Development :: Libraries
